[
    {
        "header": "Search",
        "title": "Searched for 9150 - 4600",
        "titleUrl": "https://www.google.com/search?q=9150+-+4600",
        "time": "2020-03-28T11:38:29.705Z",
        "products": [
            "Search"
        ],
        "locationInfos": [
            {
                "name": "At this general area",
                "url": "https://www.google.com/maps/@?api=1&map_action=map&center=40.148338,44.499454&zoom=12",
                "source": "From your device"
            }
        ]
    },
    {
        "header": "Search",
        "title": "Searched for 7350 pound to usd",
        "titleUrl": "https://www.google.com/search?q=7350+pound+to+usd",
        "time": "2020-03-28T11:36:29.243Z",
        "products": [
            "Search"
        ],
        "locationInfos": [
            {
                "name": "At this general area",
                "url": "https://www.google.com/maps/@?api=1&map_action=map&center=40.148338,44.499454&zoom=12",
                "source": "From your device"
            }
        ]
    },
    {
        "header": "Search",
        "title": "Searched for linklaters",
        "titleUrl": "https://www.google.com/search?q=linklaters",
        "time": "2020-03-28T10:01:37.484Z",
        "products": [
            "Search"
        ],
        "locationInfos": [
            {
                "name": "At this general area",
                "url": "https://www.google.com/maps/@?api=1&map_action=map&center=40.148338,44.499454&zoom=12",
                "source": "From your device"
            }
        ]
    },
    {
        "header": "Search",
        "title": "Searched for rachel teller",
        "titleUrl": "https://www.google.com/search?q=rachel+teller",
        "time": "2020-03-28T09:46:35.173Z",
        "products": [
            "Search"
        ],
        "locationInfos": [
            {
                "name": "At this general area",
                "url": "https://www.google.com/maps/@?api=1&map_action=map&center=40.148338,44.499454&zoom=12",
                "source": "From your device"
            }
        ]
    },
    {
        "header": "Search",
        "title": "Searched for search with image google",
        "titleUrl": "https://www.google.com/search?q=search+with+image+google",
        "time": "2020-03-28T09:37:48.215Z",
        "products": [
            "Search"
        ],
        "locationInfos": [
            {
                "name": "At this general area",
                "url": "https://www.google.com/maps/@?api=1&map_action=map&center=40.148338,44.499454&zoom=12",
                "source": "From your device"
            }
        ]
    },
    {
        "header": "Search",
        "title": "Searched for q-learning in batch version",
        "titleUrl": "https://www.google.com/search?q=q-learning+in+batch+version",
        "time": "2020-03-28T08:35:04.368Z",
        "products": [
            "Search"
        ],
        "locationInfos": [
            {
                "name": "At this general area",
                "url": "https://www.google.com/maps/@?api=1&map_action=map&center=40.148338,44.499454&zoom=12",
                "source": "From your device"
            }
        ]
    },
    {
        "header": "Search",
        "title": "Searched for Q-learning in batch version",
        "titleUrl": "https://www.google.com/search?q=Q-learning+in+batch+version",
        "time": "2020-03-28T08:31:51.444Z",
        "products": [
            "Search"
        ],
        "locationInfos": [
            {
                "name": "At this general area",
                "url": "https://www.google.com/maps/@?api=1&map_action=map&center=40.148338,44.499454&zoom=12",
                "source": "From your device"
            }
        ]
    },
    {
        "header": "Search",
        "title": "Searched for geometric sum formula",
        "titleUrl": "https://www.google.com/search?q=geometric+sum+formula",
        "time": "2020-03-27T18:26:26.356Z",
        "products": [
            "Search"
        ],
        "locationInfos": [
            {
                "name": "At this general area",
                "url": "https://www.google.com/maps/@?api=1&map_action=map&center=40.148338,44.499454&zoom=12",
                "source": "From your device"
            }
        ]
    },
    {
        "header": "Search",
        "title": "Searched for cube projection",
        "titleUrl": "https://www.google.com/search?q=cube+projection",
        "time": "2020-03-27T15:47:05.108Z",
        "products": [
            "Search"
        ],
        "locationInfos": [
            {
                "name": "At this general area",
                "url": "https://www.google.com/maps/@?api=1&map_action=map&center=40.148338,44.499454&zoom=12",
                "source": "From your device"
            }
        ]
    },
    {
        "header": "Search",
        "title": "Searched for 3d body projection formula on 2d",
        "titleUrl": "https://www.google.com/search?q=3d+body+projection+formula+on+2d",
        "time": "2020-03-27T15:44:08.938Z",
        "products": [
            "Search"
        ]
    },
    {
        "header": "Search",
        "title": "Searched for ||B||sin θ + bB(φ)h cos θ.",
        "titleUrl": "https://www.google.com/search?q=%7C%7CB%7C%7Csin+%CE%B8+%2B+bB(%CF%86)h+cos+%CE%B8.",
        "time": "2020-03-27T15:42:48.887Z",
        "products": [
            "Search"
        ],
        "locationInfos": [
            {
                "name": "At this general area",
                "url": "https://www.google.com/maps/@?api=1&map_action=map&center=40.148338,44.499454&zoom=12",
                "source": "From your device"
            }
        ]
    },
    {
        "header": "Search",
        "title": "Searched for project 3d object to 2d plane",
        "titleUrl": "https://www.google.com/search?q=project+3d+object+to+2d+plane",
        "time": "2020-03-27T15:41:01.667Z",
        "products": [
            "Search"
        ],
        "locationInfos": [
            {
                "name": "At this general area",
                "url": "https://www.google.com/maps/@?api=1&map_action=map&center=40.148338,44.499454&zoom=12",
                "source": "From your device"
            }
        ]
    },
    {
        "header": "Search",
        "title": "Searched for project cube on a some direction to a plane",
        "titleUrl": "https://www.google.com/search?q=project+cube+on+a+some+direction+to+a+plane",
        "time": "2020-03-27T15:32:44.475Z",
        "products": [
            "Search"
        ],
        "locationInfos": [
            {
                "name": "At this general area",
                "url": "https://www.google.com/maps/@?api=1&map_action=map&center=40.148338,44.499454&zoom=12",
                "source": "From your device"
            }
        ]
    },
    {
        "header": "Search",
        "title": "Searched for project cube on a some direction to a plane python",
        "titleUrl": "https://www.google.com/search?q=project+cube+on+a+some+direction+to+a+plane+python",
        "time": "2020-03-27T15:32:42.324Z",
        "products": [
            "Search"
        ],
        "locationInfos": [
            {
                "name": "At this general area",
                "url": "https://www.google.com/maps/@?api=1&map_action=map&center=40.148338,44.499454&zoom=12",
                "source": "From your device"
            }
        ]
    },
    {
        "header": "Search",
        "title": "Searched for right trapezoidal parallelepiped",
        "titleUrl": "https://www.google.com/search?q=right+trapezoidal+parallelepiped",
        "time": "2020-03-27T14:42:54.483Z",
        "products": [
            "Search"
        ],
        "locationInfos": [
            {
                "name": "At this general area",
                "url": "https://www.google.com/maps/@?api=1&map_action=map&center=40.148338,44.499454&zoom=12",
                "source": "From your device"
            }
        ]
    },
    {
        "header": "Search",
        "title": "Searched for right rectangular parallelepiped",
        "titleUrl": "https://www.google.com/search?q=right+rectangular+parallelepiped",
        "time": "2020-03-27T14:42:32.374Z",
        "products": [
            "Search"
        ],
        "locationInfos": [
            {
                "name": "At this general area",
                "url": "https://www.google.com/maps/@?api=1&map_action=map&center=40.148338,44.499454&zoom=12",
                "source": "From your device"
            }
        ]
    },
    {
        "header": "Search",
        "title": "Searched for bellman equation explained",
        "titleUrl": "https://www.google.com/search?q=bellman+equation+explained",
        "time": "2020-03-27T10:43:01.062Z",
        "products": [
            "Search"
        ],
        "locationInfos": [
            {
                "name": "At this general area",
                "url": "https://www.google.com/maps/@?api=1&map_action=map&center=40.148338,44.499454&zoom=12",
                "source": "From your device"
            }
        ]
    },
    {
        "header": "Search",
        "title": "Searched for 108/36mes",
        "titleUrl": "https://www.google.com/search?q=108/36mes",
        "time": "2020-03-27T10:05:05.707Z",
        "products": [
            "Search"
        ],
        "locationInfos": [
            {
                "name": "At this general area",
                "url": "https://www.google.com/maps/@?api=1&map_action=map&center=40.148338,44.499454&zoom=12",
                "source": "From your device"
            }
        ]
    },
    {
        "header": "Search",
        "title": "Searched for signum",
        "titleUrl": "https://www.google.com/search?q=signum",
        "time": "2020-03-27T08:12:03.168Z",
        "products": [
            "Search"
        ],
        "locationInfos": [
            {
                "name": "At this general area",
                "url": "https://www.google.com/maps/@?api=1&map_action=map&center=40.148338,44.499454&zoom=12",
                "source": "From your device"
            }
        ]
    },
    {
        "header": "Search",
        "title": "Searched for perceptron algorithm activation function",
        "titleUrl": "https://www.google.com/search?q=perceptron+algorithm+activation+function",
        "time": "2020-03-27T08:09:55.516Z",
        "products": [
            "Search"
        ],
        "locationInfos": [
            {
                "name": "At this general area",
                "url": "https://www.google.com/maps/@?api=1&map_action=map&center=40.148338,44.499454&zoom=12",
                "source": "From your device"
            }
        ]
    },
    {
        "header": "Search",
        "title": "Searched for Wulfram Gerstner",
        "titleUrl": "https://www.google.com/search?q=Wulfram+Gerstner",
        "time": "2020-03-27T07:44:16.886Z",
        "products": [
            "Search"
        ],
        "locationInfos": [
            {
                "name": "At this general area",
                "url": "https://www.google.com/maps/@?api=1&map_action=map&center=40.148338,44.499454&zoom=12",
                "source": "From your device"
            }
        ]
    },
    {
        "header": "Search",
        "title": "Searched for Paris Fury",
        "titleUrl": "https://www.google.com/search?q=Paris+Fury",
        "time": "2020-03-26T19:29:16.063Z",
        "products": [
            "Search"
        ],
        "locationInfos": [
            {
                "name": "At this general area",
                "url": "https://www.google.com/maps/@?api=1&map_action=map&center=40.148338,44.499454&zoom=12",
                "source": "From your device"
            }
        ]
    },
    {
        "header": "Search",
        "title": "Searched for tyson fury",
        "titleUrl": "https://www.google.com/search?q=tyson+fury",
        "time": "2020-03-26T19:28:55.463Z",
        "products": [
            "Search"
        ],
        "locationInfos": [
            {
                "name": "At this general area",
                "url": "https://www.google.com/maps/@?api=1&map_action=map&center=40.148338,44.499454&zoom=12",
                "source": "From your device"
            }
        ]
    },
    {
        "header": "Search",
        "title": "Searched for слизевик",
        "titleUrl": "https://www.google.com/search?q=%D1%81%D0%BB%D0%B8%D0%B7%D0%B5%D0%B2%D0%B8%D0%BA",
        "time": "2020-03-26T19:21:17.962Z",
        "products": [
            "Search"
        ],
        "locationInfos": [
            {
                "name": "At this general area",
                "url": "https://www.google.com/maps/@?api=1&map_action=map&center=40.148338,44.499454&zoom=12",
                "source": "From your device"
            }
        ]
    },
    {
        "header": "Search",
        "title": "Searched for anna ananova google scholar",
        "titleUrl": "https://www.google.com/search?q=anna+ananova+google+scholar",
        "time": "2020-03-26T19:09:25.142Z",
        "products": [
            "Search"
        ],
        "locationInfos": [
            {
                "name": "At this general area",
                "url": "https://www.google.com/maps/@?api=1&map_action=map&center=40.148338,44.499454&zoom=12",
                "source": "From your device"
            }
        ]
    },
    {
        "header": "Search",
        "title": "Searched for eleni oragir seria 11",
        "titleUrl": "https://www.google.com/search?q=eleni+oragir+seria+11",
        "time": "2018-07-16T20:43:57.253Z",
        "products": [
            "Search"
        ]
    },
    {
        "header": "Search",
        "title": "Searched for ValueError: 3-dimensional arrays must be of dtype unsigned byte, unsigned short, float32 or float64",
        "titleUrl": "https://www.google.com/search?q=ValueError:+3-dimensional+arrays+must+be+of+dtype+unsigned+byte,+unsigned+short,+float32+or+float64",
        "time": "2018-07-16T17:30:44.518Z",
        "products": [
            "Search"
        ]
    },
    {
        "header": "Search",
        "title": "Searched for how to feed image to k means",
        "titleUrl": "https://www.google.com/search?q=how+to+feed+image+to+k+means",
        "time": "2018-07-16T17:25:25.356Z",
        "products": [
            "Search"
        ]
    },
    {
        "header": "Search",
        "title": "Searched for how to feed image to kmeans",
        "titleUrl": "https://www.google.com/search?q=how+to+feed+image+to+kmeans",
        "time": "2018-07-16T17:25:22.576Z",
        "products": [
            "Search"
        ]
    },
    {
        "header": "Search",
        "title": "Searched for numpy reshape",
        "titleUrl": "https://www.google.com/search?q=numpy+reshape",
        "time": "2018-07-16T17:19:45.911Z",
        "products": [
            "Search"
        ]
    },
    {
        "header": "Search",
        "title": "Searched for how to fit image to kmeans",
        "titleUrl": "https://www.google.com/search?q=how+to+fit+image+to+kmeans",
        "time": "2018-07-16T17:18:59.049Z",
        "products": [
            "Search"
        ]
    },
    {
        "header": "Search",
        "title": "Searched for np tile for columns",
        "titleUrl": "https://www.google.com/search?q=np+tile+for+columns",
        "time": "2018-07-16T17:11:04.943Z",
        "products": [
            "Search"
        ]
    },
    {
        "header": "Search",
        "title": "Searched for how to duplicate columns in numpy array",
        "titleUrl": "https://www.google.com/search?q=how+to+duplicate+columns+in+numpy+array",
        "time": "2018-07-16T17:08:43.018Z",
        "products": [
            "Search"
        ]
    },
    {
        "header": "Search",
        "title": "Searched for how to duplicate numpy array",
        "titleUrl": "https://www.google.com/search?q=how+to+duplicate+numpy+array",
        "time": "2018-07-16T17:05:24.473Z",
        "products": [
            "Search"
        ]
    },
    {
        "header": "Search",
        "title": "Searched for opencv install python mac conda",
        "titleUrl": "https://www.google.com/search?q=opencv+install+python+mac+conda",
        "time": "2018-07-16T16:54:01.640Z",
        "products": [
            "Search"
        ]
    },
    {
        "header": "Search",
        "title": "Searched for opencv install python mac",
        "titleUrl": "https://www.google.com/search?q=opencv+install+python+mac",
        "time": "2018-07-16T16:53:46.095Z",
        "products": [
            "Search"
        ]
    },
    {
        "header": "Search",
        "title": "Searched for imageio imread grayscale",
        "titleUrl": "https://www.google.com/search?q=imageio+imread+grayscale",
        "time": "2018-07-16T16:50:57.278Z",
        "products": [
            "Search"
        ]
    },
    {
        "header": "Search",
        "title": "Searched for imageio imread",
        "titleUrl": "https://www.google.com/search?q=imageio+imread",
        "time": "2018-07-16T16:50:12.215Z",
        "products": [
            "Search"
        ]
    },
    {
        "header": "Search",
        "title": "Searched for imread python",
        "titleUrl": "https://www.google.com/search?q=imread+python",
        "time": "2018-07-16T16:49:50.691Z",
        "products": [
            "Search"
        ]
    },
    {
        "header": "Search",
        "title": "Searched for libopencv_imgcodecs.3.3.dylib requires version 9.0.0 or later, but libtiff.5.dylib provides version 8.0.0",
        "titleUrl": "https://www.google.com/search?q=libopencv_imgcodecs.3.3.dylib+requires+version+9.0.0+or+later,+but+libtiff.5.dylib+provides+version+8.0.0",
        "time": "2018-07-16T16:47:34.016Z",
        "products": [
            "Search"
        ]
    },
    {
        "header": "Search",
        "title": "Searched for No module named 'cv2'",
        "titleUrl": "https://www.google.com/search?q=No+module+named+%27cv2%27",
        "time": "2018-07-16T16:45:22.277Z",
        "products": [
            "Search"
        ]
    },
    {
        "header": "Search",
        "title": "Searched for conda install opencv",
        "titleUrl": "https://www.google.com/search?q=conda+install+opencv",
        "time": "2018-07-16T16:44:23.221Z",
        "products": [
            "Search"
        ]
    },
    {
        "header": "Search",
        "title": "Searched for conda install cv2",
        "titleUrl": "https://www.google.com/search?q=conda+install+cv2",
        "time": "2018-07-16T16:43:59.094Z",
        "products": [
            "Search"
        ]
    },
    {
        "header": "Search",
        "title": "Searched for python load grayscale image",
        "titleUrl": "https://www.google.com/search?q=python+load+grayscale+image",
        "time": "2018-07-16T16:40:06.555Z",
        "products": [
            "Search"
        ]
    },
    {
        "header": "Search",
        "title": "Searched for python load image",
        "titleUrl": "https://www.google.com/search?q=python+load+image",
        "time": "2018-07-16T16:39:46.671Z",
        "products": [
            "Search"
        ]
    },
    {
        "header": "Search",
        "title": "Searched for opencv install python",
        "titleUrl": "https://www.google.com/search?q=opencv+install+python",
        "time": "2018-07-16T16:36:08.554Z",
        "products": [
            "Search"
        ]
    },
    {
        "header": "Search",
        "title": "Searched for image reading in python",
        "titleUrl": "https://www.google.com/search?q=image+reading+in+python",
        "time": "2018-07-16T16:35:53.092Z",
        "products": [
            "Search"
        ]
    },
    {
        "header": "Search",
        "title": "Searched for how to load grayscale image in python",
        "titleUrl": "https://www.google.com/search?q=how+to+load+grayscale+image+in+python",
        "time": "2018-07-16T16:33:05.202Z",
        "products": [
            "Search"
        ]
    },
    {
        "header": "Search",
        "title": "Searched for conda uninstall",
        "titleUrl": "https://www.google.com/search?q=conda+uninstall",
        "time": "2018-07-16T16:32:00.660Z",
        "products": [
            "Search"
        ]
    },
    {
        "header": "Search",
        "title": "Searched for how to remove opencv conda",
        "titleUrl": "https://www.google.com/search?q=how+to+remove+opencv+conda",
        "time": "2018-07-16T16:31:54.959Z",
        "products": [
            "Search"
        ]
    },
    {
        "header": "Search",
        "title": "Searched for how to remove conda install",
        "titleUrl": "https://www.google.com/search?q=how+to+remove+conda+install",
        "time": "2018-07-16T16:31:27.823Z",
        "products": [
            "Search"
        ]
    },
    {
        "header": "Search",
        "title": "Searched for how to uninstall opencv in anaconda",
        "titleUrl": "https://www.google.com/search?q=how+to+uninstall+opencv+in+anaconda",
        "time": "2018-07-16T16:30:57.875Z",
        "products": [
            "Search"
        ]
    },
    {
        "header": "Search",
        "title": "Searched for how to install opencv in anaconda",
        "titleUrl": "https://www.google.com/search?q=how+to+install+opencv+in+anaconda",
        "time": "2018-07-16T16:30:40.309Z",
        "products": [
            "Search"
        ]
    },
    {
        "header": "Search",
        "title": "Searched for imread python grayscale",
        "titleUrl": "https://www.google.com/search?q=imread+python+grayscale",
        "time": "2018-07-16T16:28:24.605Z",
        "products": [
            "Search"
        ]
    },
    {
        "header": "Search",
        "title": "Searched for how to load image in python",
        "titleUrl": "https://www.google.com/search?q=how+to+load+image+in+python",
        "time": "2018-07-16T16:22:54.323Z",
        "products": [
            "Search"
        ]
    },
    {
        "header": "Search",
        "title": "Searched for dvm",
        "titleUrl": "https://www.google.com/search?q=dvm",
        "time": "2018-07-16T13:37:20.373Z",
        "products": [
            "Search"
        ]
    },
    {
        "header": "Search",
        "title": "Searched for k means on image",
        "titleUrl": "https://www.google.com/search?q=k+means+on+image",
        "time": "2018-07-16T09:50:28.317Z",
        "products": [
            "Search"
        ]
    },
    {
        "header": "Search",
        "title": "Searched for normalize image python",
        "titleUrl": "https://www.google.com/search?q=normalize+image+python",
        "time": "2018-07-16T09:38:21.489Z",
        "products": [
            "Search"
        ]
    },
    {
        "header": "Search",
        "title": "Searched for imread python",
        "titleUrl": "https://www.google.com/search?q=imread+python",
        "time": "2018-07-16T08:54:46.319Z",
        "products": [
            "Search"
        ]
    },
    {
        "header": "Search",
        "title": "Searched for load jpg python",
        "titleUrl": "https://www.google.com/search?q=load+jpg+python",
        "time": "2018-07-16T08:54:20.793Z",
        "products": [
            "Search"
        ]
    },
    {
        "header": "Search",
        "title": "Searched for how to sum columns of 2 dimensional arrays within 3 dimensional array in python",
        "titleUrl": "https://www.google.com/search?q=how+to+sum+columns+of+2+dimensional+arrays+within+3+dimensional+array+in+python",
        "time": "2018-07-15T21:20:15.194Z",
        "products": [
            "Search"
        ]
    },
    {
        "header": "Search",
        "title": "Searched for how to sum columns of 3 dimensional array in python",
        "titleUrl": "https://www.google.com/search?q=how+to+sum+columns+of+3+dimensional+array+in+python",
        "time": "2018-07-15T21:19:54.440Z",
        "products": [
            "Search"
        ]
    },
    {
        "header": "Search",
        "title": "Searched for how to fill numpy array except for diagonal",
        "titleUrl": "https://www.google.com/search?q=how+to+fill+numpy+array+except+for+diagonal",
        "time": "2018-07-15T21:03:46.122Z",
        "products": [
            "Search"
        ]
    },
    {
        "header": "Search",
        "title": "Searched for how to create numpy array array with some value on main diagonal and all others",
        "titleUrl": "https://www.google.com/search?q=how+to+create+numpy+array+array+with+some+value+on+main+diagonal+and+all+others",
        "time": "2018-07-15T21:03:08.855Z",
        "products": [
            "Search"
        ]
    },
    {
        "header": "Search",
        "title": "Searched for batch normalization python code",
        "titleUrl": "https://www.google.com/search?q=batch+normalization+python+code",
        "time": "2018-07-15T19:52:52.085Z",
        "products": [
            "Search"
        ]
    },
    {
        "header": "Search",
        "title": "Searched for car overtaking cars game friv",
        "titleUrl": "https://www.google.com/search?q=car+overtaking+cars+game+friv",
        "time": "2018-07-15T17:49:34.892Z",
        "products": [
            "Search"
        ]
    },
    {
        "header": "Search",
        "title": "Searched for roger federer",
        "titleUrl": "https://www.google.com/search?q=roger+federer",
        "time": "2018-07-15T16:53:43.936Z",
        "products": [
            "Search"
        ]
    },
    {
        "header": "Search",
        "title": "Searched for federer",
        "titleUrl": "https://www.google.com/search?q=federer",
        "time": "2018-07-15T16:52:55.849Z",
        "products": [
            "Search"
        ]
    },
    {
        "header": "Search",
        "title": "Searched for novak djokovic",
        "titleUrl": "https://www.google.com/search?q=novak+djokovic",
        "time": "2018-07-15T16:52:12.318Z",
        "products": [
            "Search"
        ]
    },
    {
        "header": "Search",
        "title": "Searched for kylian mbappe",
        "titleUrl": "https://www.google.com/search?q=kylian+mbappe",
        "time": "2018-07-15T16:37:51.692Z",
        "products": [
            "Search"
        ]
    },
    {
        "header": "Search",
        "title": "Searched for yerevan map",
        "titleUrl": "https://www.google.com/search?q=yerevan+map",
        "time": "2018-07-15T08:23:29.924Z",
        "products": [
            "Search"
        ]
    },
    {
        "header": "Search",
        "title": "Searched for ջրվեժի արգելանոց",
        "titleUrl": "https://www.google.com/search?q=%D5%BB%D6%80%D5%BE%D5%A5%D5%AA%D5%AB+%D5%A1%D6%80%D5%A3%D5%A5%D5%AC%D5%A1%D5%B6%D5%B8%D6%81",
        "time": "2018-07-15T08:22:30.172Z",
        "products": [
            "Search"
        ]
    },
    {
        "header": "Search",
        "title": "Searched for վարձով օրական տուն",
        "titleUrl": "https://www.google.com/search?q=%D5%BE%D5%A1%D6%80%D5%B1%D5%B8%D5%BE+%D6%85%D6%80%D5%A1%D5%AF%D5%A1%D5%B6+%D5%BF%D5%B8%D6%82%D5%B6",
        "time": "2018-07-14T18:51:34.698Z",
        "products": [
            "Search"
        ]
    },
    {
        "header": "Search",
        "title": "Searched for վարձով սեփական բնակարան քաղաքից դուրս",
        "titleUrl": "https://www.google.com/search?q=%D5%BE%D5%A1%D6%80%D5%B1%D5%B8%D5%BE+%D5%BD%D5%A5%D6%83%D5%A1%D5%AF%D5%A1%D5%B6+%D5%A2%D5%B6%D5%A1%D5%AF%D5%A1%D6%80%D5%A1%D5%B6+%D6%84%D5%A1%D5%B2%D5%A1%D6%84%D5%AB%D6%81+%D5%A4%D5%B8%D6%82%D6%80%D5%BD",
        "time": "2018-07-14T18:44:55.312Z",
        "products": [
            "Search"
        ]
    },
    {
        "header": "Search",
        "title": "Searched for վարձով բնակարան 40000 -50000-դրամ",
        "titleUrl": "https://www.google.com/search?q=%D5%BE%D5%A1%D6%80%D5%B1%D5%B8%D5%BE+%D5%A2%D5%B6%D5%A1%D5%AF%D5%A1%D6%80%D5%A1%D5%B6+40000+-50000-%D5%A4%D6%80%D5%A1%D5%B4",
        "time": "2018-07-14T18:44:38.447Z",
        "products": [
            "Search"
        ]
    },
    {
        "header": "Search",
        "title": "Searched for վարձով տներ",
        "titleUrl": "https://www.google.com/search?q=%D5%BE%D5%A1%D6%80%D5%B1%D5%B8%D5%BE+%D5%BF%D5%B6%D5%A5%D6%80",
        "time": "2018-07-14T18:44:19.965Z",
        "products": [
            "Search"
        ]
    },
    {
        "header": "Search",
        "title": "Searched for england",
        "titleUrl": "https://www.google.com/search?q=england",
        "time": "2018-07-14T15:52:23.992Z",
        "products": [
            "Search"
        ]
    },
    {
        "header": "Search",
        "title": "Searched for mode of numpy array in python",
        "titleUrl": "https://www.google.com/search?q=mode+of+numpy+array+in+python",
        "time": "2018-07-14T10:57:37.543Z",
        "products": [
            "Search"
        ]
    },
    {
        "header": "Search",
        "title": "Searched for mode of array in python",
        "titleUrl": "https://www.google.com/search?q=mode+of+array+in+python",
        "time": "2018-07-14T10:57:33.679Z",
        "products": [
            "Search"
        ]
    },
    {
        "header": "Search",
        "title": "Searched for mode of array",
        "titleUrl": "https://www.google.com/search?q=mode+of+array",
        "time": "2018-07-14T10:57:29.713Z",
        "products": [
            "Search"
        ]
    },
    {
        "header": "Search",
        "title": "Searched for mod of array",
        "titleUrl": "https://www.google.com/search?q=mod+of+array",
        "time": "2018-07-14T10:57:11.840Z",
        "products": [
            "Search"
        ]
    },
    {
        "header": "Search",
        "title": "Searched for how to sort a list in python",
        "titleUrl": "https://www.google.com/search?q=how+to+sort+a+list+in+python",
        "time": "2018-07-14T10:53:05.967Z",
        "products": [
            "Search"
        ],
        "locationInfos": [
            {
                "name": "At this general area",
                "url": "https://www.google.com/maps/@?api=1&map_action=map&center=40.183777,44.514705&zoom=13",
                "source": "Based on your past activity"
            }
        ]
    },
    {
        "header": "Search",
        "title": "Searched for how to sort a list",
        "titleUrl": "https://www.google.com/search?q=how+to+sort+a+list",
        "time": "2018-07-14T10:53:02.506Z",
        "products": [
            "Search"
        ]
    },
    {
        "header": "Search",
        "title": "Searched for how to sort list and get new indices",
        "titleUrl": "https://www.google.com/search?q=how+to+sort+list+and+get+new+indices",
        "time": "2018-07-14T10:50:02.990Z",
        "products": [
            "Search"
        ]
    },
    {
        "header": "Search",
        "title": "Searched for gaussian mixture model tutorial wikipedia",
        "titleUrl": "https://www.google.com/search?q=gaussian+mixture+model+tutorial+wikipedia",
        "time": "2018-07-14T09:46:23.092Z",
        "products": [
            "Search"
        ]
    },
    {
        "header": "Search",
        "title": "Searched for gaussian mixture model tutorial",
        "titleUrl": "https://www.google.com/search?q=gaussian+mixture+model+tutorial",
        "time": "2018-07-14T09:42:44.948Z",
        "products": [
            "Search"
        ]
    },
    {
        "header": "Search",
        "title": "Searched for gmm algorithm",
        "titleUrl": "https://www.google.com/search?q=gmm+algorithm",
        "time": "2018-07-14T09:42:34.261Z",
        "products": [
            "Search"
        ]
    },
    {
        "header": "Search",
        "title": "Searched for gmm alex cotton candy hair",
        "titleUrl": "https://www.google.com/search?q=gmm+alex+cotton+candy+hair",
        "time": "2018-07-14T09:42:27.885Z",
        "products": [
            "Search"
        ]
    },
    {
        "header": "Search",
        "title": "Searched for what is hadoop",
        "titleUrl": "https://www.google.com/search?q=what+is+hadoop",
        "time": "2018-07-13T13:26:59.206Z",
        "products": [
            "Search"
        ],
        "locationInfos": [
            {
                "name": "At this general area",
                "url": "https://www.google.com/maps/@?api=1&map_action=map&center=40.183777,44.514705&zoom=11",
                "source": "Based on your past activity"
            }
        ]
    },
    {
        "header": "Search",
        "title": "Searched for k means++ explanation",
        "titleUrl": "https://www.google.com/search?q=k+means%2B%2B+explanation",
        "time": "2018-07-13T13:21:33.678Z",
        "products": [
            "Search"
        ],
        "locationInfos": [
            {
                "name": "At this general area",
                "url": "https://www.google.com/maps/@?api=1&map_action=map&center=40.183777,44.514705&zoom=11",
                "source": "Based on your past activity"
            }
        ]
    },
    {
        "header": "Search",
        "title": "Searched for arsen mamikonyan",
        "titleUrl": "https://www.google.com/search?q=arsen+mamikonyan",
        "time": "2018-07-13T13:02:42.005Z",
        "products": [
            "Search"
        ],
        "locationInfos": [
            {
                "name": "At this general area",
                "url": "https://www.google.com/maps/@?api=1&map_action=map&center=40.183777,44.514705&zoom=11",
                "source": "Based on your past activity"
            }
        ]
    },
    {
        "header": "Search",
        "title": "Searched for k means++",
        "titleUrl": "https://www.google.com/search?q=k+means%2B%2B",
        "time": "2018-07-13T12:38:05.788Z",
        "products": [
            "Search"
        ],
        "locationInfos": [
            {
                "name": "At this general area",
                "url": "https://www.google.com/maps/@?api=1&map_action=map&center=40.183777,44.514705&zoom=11",
                "source": "Based on your past activity"
            }
        ]
    },
    {
        "header": "Search",
        "title": "Searched for the distance between midpoint and all points from each other",
        "titleUrl": "https://www.google.com/search?q=the+distance+between+midpoint+and+all+points+from+each+other",
        "time": "2018-07-13T12:26:32.725Z",
        "products": [
            "Search"
        ],
        "locationInfos": [
            {
                "name": "At this general area",
                "url": "https://www.google.com/maps/@?api=1&map_action=map&center=40.183777,44.514705&zoom=11",
                "source": "Based on your past activity"
            }
        ]
    },
    {
        "header": "Search",
        "title": "Searched for lgb machine learning",
        "titleUrl": "https://www.google.com/search?q=lgb+machine+learning",
        "time": "2018-07-12T22:19:01.053Z",
        "products": [
            "Search"
        ],
        "locationInfos": [
            {
                "name": "At this general area",
                "url": "https://www.google.com/maps/@?api=1&map_action=map&center=40.183777,44.514705&zoom=11",
                "source": "Based on your past activity"
            }
        ]
    },
    {
        "header": "Search",
        "title": "Searched for lgb",
        "titleUrl": "https://www.google.com/search?q=lgb",
        "time": "2018-07-12T22:18:56.590Z",
        "products": [
            "Search"
        ],
        "locationInfos": [
            {
                "name": "At this general area",
                "url": "https://www.google.com/maps/@?api=1&map_action=map&center=40.183777,44.514705&zoom=11",
                "source": "Based on your past activity"
            }
        ]
    },
    {
        "header": "Search",
        "title": "Searched for c++ set insert complexity",
        "titleUrl": "https://www.google.com/search?q=c%2B%2B+set+insert+complexity",
        "time": "2018-07-12T22:16:19.708Z",
        "products": [
            "Search"
        ],
        "locationInfos": [
            {
                "name": "At this general area",
                "url": "https://www.google.com/maps/@?api=1&map_action=map&center=40.183777,44.514705&zoom=11",
                "source": "Based on your past activity"
            }
        ]
    },
    {
        "header": "Search",
        "title": "Searched for c++ set insert running time",
        "titleUrl": "https://www.google.com/search?q=c%2B%2B+set+insert+running+time",
        "time": "2018-07-12T22:14:32.524Z",
        "products": [
            "Search"
        ],
        "locationInfos": [
            {
                "name": "At this general area",
                "url": "https://www.google.com/maps/@?api=1&map_action=map&center=40.183777,44.514705&zoom=11",
                "source": "Based on your past activity"
            }
        ]
    },
    {
        "header": "Search",
        "title": "Searched for c++ set insert",
        "titleUrl": "https://www.google.com/search?q=c%2B%2B+set+insert",
        "time": "2018-07-12T22:12:37.616Z",
        "products": [
            "Search"
        ],
        "locationInfos": [
            {
                "name": "At this general area",
                "url": "https://www.google.com/maps/@?api=1&map_action=map&center=40.183777,44.514705&zoom=11",
                "source": "Based on your past activity"
            }
        ]
    },
    {
        "header": "Search",
        "title": "Searched for set insert complexity",
        "titleUrl": "https://www.google.com/search?q=set+insert+complexity",
        "time": "2018-07-12T22:08:44.620Z",
        "products": [
            "Search"
        ],
        "locationInfos": [
            {
                "name": "At this general area",
                "url": "https://www.google.com/maps/@?api=1&map_action=map&center=40.183777,44.514705&zoom=11",
                "source": "Based on your past activity"
            }
        ]
    },
    {
        "header": "Search",
        "title": "Searched for given holes catch mice math problem",
        "titleUrl": "https://www.google.com/search?q=given+holes+catch+mice+math+problem",
        "time": "2018-07-12T21:56:58.488Z",
        "products": [
            "Search"
        ],
        "locationInfos": [
            {
                "name": "At this general area",
                "url": "https://www.google.com/maps/@?api=1&map_action=map&center=40.183777,44.514705&zoom=11",
                "source": "Based on your past activity"
            }
        ]
    },
    {
        "header": "Search",
        "title": "Searched for given holes catch mice",
        "titleUrl": "https://www.google.com/search?q=given+holes+catch+mice",
        "time": "2018-07-12T21:56:51.961Z",
        "products": [
            "Search"
        ],
        "locationInfos": [
            {
                "name": "At this general area",
                "url": "https://www.google.com/maps/@?api=1&map_action=map&center=40.183777,44.514705&zoom=11",
                "source": "Based on your past activity"
            }
        ]
    },
    {
        "header": "Search",
        "title": "Searched for 5 holes and mouse problem",
        "titleUrl": "https://www.google.com/search?q=5+holes+and+mouse+problem",
        "time": "2018-07-12T21:05:23.261Z",
        "products": [
            "Search"
        ],
        "locationInfos": [
            {
                "name": "At this general area",
                "url": "https://www.google.com/maps/@?api=1&map_action=map&center=40.183777,44.514705&zoom=11",
                "source": "Based on your past activity"
            }
        ]
    },
    {
        "header": "Search",
        "title": "Searched for 5 holes and mice problem",
        "titleUrl": "https://www.google.com/search?q=5+holes+and+mice+problem",
        "time": "2018-07-12T21:05:17.212Z",
        "products": [
            "Search"
        ],
        "locationInfos": [
            {
                "name": "At this general area",
                "url": "https://www.google.com/maps/@?api=1&map_action=map&center=40.183777,44.514705&zoom=11",
                "source": "Based on your past activity"
            }
        ]
    },
    {
        "header": "Search",
        "title": "Searched for Pollyanna Uruena",
        "titleUrl": "https://www.google.com/search?q=Pollyanna+Uruena",
        "time": "2018-07-12T20:27:55.222Z",
        "products": [
            "Search"
        ],
        "locationInfos": [
            {
                "name": "At this general area",
                "url": "https://www.google.com/maps/@?api=1&map_action=map&center=40.183777,44.514705&zoom=11",
                "source": "Based on your past activity"
            }
        ]
    },
    {
        "header": "Search",
        "title": "Searched for SEE RANK Pollyanna Uruena",
        "titleUrl": "https://www.google.com/search?q=SEE+RANK+Pollyanna+Uruena",
        "time": "2018-07-12T20:27:11.109Z",
        "products": [
            "Search"
        ],
        "locationInfos": [
            {
                "name": "At this general area",
                "url": "https://www.google.com/maps/@?api=1&map_action=map&center=40.183777,44.514705&zoom=11",
                "source": "Based on your past activity"
            }
        ]
    },
    {
        "header": "Search",
        "title": "Searched for Enrique Iglesias - EL BAÑO ft. Bad Bunny girl name",
        "titleUrl": "https://www.google.com/search?q=Enrique+Iglesias+-+EL+BA%C3%91O+ft.+Bad+Bunny+girl+name",
        "time": "2018-07-12T20:26:58.552Z",
        "products": [
            "Search"
        ],
        "locationInfos": [
            {
                "name": "At this general area",
                "url": "https://www.google.com/maps/@?api=1&map_action=map&center=40.183777,44.514705&zoom=11",
                "source": "Based on your past activity"
            }
        ]
    },
    {
        "header": "Search",
        "title": "Searched for Enrique Iglesias - EL BAÑO ft. Bad Bunny",
        "titleUrl": "https://www.google.com/search?q=Enrique+Iglesias+-+EL+BA%C3%91O+ft.+Bad+Bunny",
        "time": "2018-07-12T20:26:01.710Z",
        "products": [
            "Search"
        ],
        "locationInfos": [
            {
                "name": "At this general area",
                "url": "https://www.google.com/maps/@?api=1&map_action=map&center=40.183777,44.514705&zoom=11",
                "source": "Based on your past activity"
            }
        ]
    },
    {
        "header": "Search",
        "title": "Searched for ermina zakharova instagram",
        "titleUrl": "https://www.google.com/search?q=ermina+zakharova+instagram",
        "time": "2018-07-12T19:36:09.409Z",
        "products": [
            "Search"
        ],
        "locationInfos": [
            {
                "name": "At this general area",
                "url": "https://www.google.com/maps/@?api=1&map_action=map&center=40.183777,44.514705&zoom=11",
                "source": "Based on your past activity"
            }
        ]
    },
    {
        "header": "Search",
        "title": "Searched for ermina voske dproc instagram",
        "titleUrl": "https://www.google.com/search?q=ermina+voske+dproc+instagram",
        "time": "2018-07-12T19:35:57.300Z",
        "products": [
            "Search"
        ],
        "locationInfos": [
            {
                "name": "At this general area",
                "url": "https://www.google.com/maps/@?api=1&map_action=map&center=40.183777,44.514705&zoom=11",
                "source": "Based on your past activity"
            }
        ]
    },
    {
        "header": "Search",
        "title": "Searched for ermina",
        "titleUrl": "https://www.google.com/search?q=ermina",
        "time": "2018-07-12T19:35:06.157Z",
        "products": [
            "Search"
        ],
        "locationInfos": [
            {
                "name": "At this general area",
                "url": "https://www.google.com/maps/@?api=1&map_action=map&center=40.183777,44.514705&zoom=11",
                "source": "Based on your past activity"
            }
        ]
    },
    {
        "header": "Search",
        "title": "Searched for voske dproc",
        "titleUrl": "https://www.google.com/search?q=voske+dproc&tbm=vid",
        "time": "2018-07-12T19:32:25.293Z",
        "products": [
            "Search"
        ],
        "locationInfos": [
            {
                "name": "At this general area",
                "url": "https://www.google.com/maps/@?api=1&map_action=map&center=40.183777,44.514705&zoom=11",
                "source": "Based on your past activity"
            }
        ]
    },
    {
        "header": "Search",
        "title": "Searched for voske dproc",
        "titleUrl": "https://www.google.com/search?q=voske+dproc",
        "time": "2018-07-12T19:32:20.928Z",
        "products": [
            "Search"
        ],
        "locationInfos": [
            {
                "name": "At this general area",
                "url": "https://www.google.com/maps/@?api=1&map_action=map&center=40.183777,44.514705&zoom=11",
                "source": "Based on your past activity"
            }
        ]
    },
    {
        "header": "Search",
        "title": "Searched for magoosh flashcards words",
        "titleUrl": "https://www.google.com/search?q=magoosh+flashcards+words",
        "time": "2018-07-12T13:07:39.963Z",
        "products": [
            "Search"
        ],
        "locationInfos": [
            {
                "name": "At this general area",
                "url": "https://www.google.com/maps/@?api=1&map_action=map&center=40.183777,44.514705&zoom=11",
                "source": "Based on your past activity"
            }
        ]
    },
    {
        "header": "Search",
        "title": "Searched for magoosh vocabulary",
        "titleUrl": "https://www.google.com/search?q=magoosh+vocabulary",
        "time": "2018-07-12T13:04:01.836Z",
        "products": [
            "Search"
        ],
        "locationInfos": [
            {
                "name": "At this general area",
                "url": "https://www.google.com/maps/@?api=1&map_action=map&center=40.183777,44.514705&zoom=11",
                "source": "Based on your past activity"
            }
        ]
    },
    {
        "header": "Search",
        "title": "Searched for magoosh",
        "titleUrl": "https://www.google.com/search?q=magoosh",
        "time": "2018-07-12T13:03:58.357Z",
        "products": [
            "Search"
        ],
        "locationInfos": [
            {
                "name": "At this general area",
                "url": "https://www.google.com/maps/@?api=1&map_action=map&center=40.183777,44.514705&zoom=11",
                "source": "Based on your past activity"
            }
        ]
    },
    {
        "header": "Search",
        "title": "Searched for kaskadyor",
        "titleUrl": "https://www.google.com/search?q=kaskadyor",
        "time": "2018-07-12T11:52:17.648Z",
        "products": [
            "Search"
        ],
        "locationInfos": [
            {
                "name": "At this general area",
                "url": "https://www.google.com/maps/@?api=1&map_action=map&center=40.183777,44.514705&zoom=11",
                "source": "Based on your past activity"
            }
        ]
    },
    {
        "header": "Search",
        "title": "Searched for plotly gradient boosting scikit learn",
        "titleUrl": "https://www.google.com/search?q=plotly+gradient+boosting+scikit+learn",
        "time": "2018-07-12T08:37:33.102Z",
        "products": [
            "Search"
        ],
        "locationInfos": [
            {
                "name": "At this general area",
                "url": "https://www.google.com/maps/@?api=1&map_action=map&center=40.183777,44.514705&zoom=11",
                "source": "Based on your past activity"
            }
        ]
    },
    {
        "header": "Search",
        "title": "Searched for plotly gradient boosting",
        "titleUrl": "https://www.google.com/search?q=plotly+gradient+boosting",
        "time": "2018-07-12T08:36:45.691Z",
        "products": [
            "Search"
        ],
        "locationInfos": [
            {
                "name": "At this general area",
                "url": "https://www.google.com/maps/@?api=1&map_action=map&center=40.183777,44.514705&zoom=11",
                "source": "Based on your past activity"
            }
        ]
    },
    {
        "header": "Search",
        "title": "Searched for plotly gradient boosting feature importances",
        "titleUrl": "https://www.google.com/search?q=plotly+gradient+boosting+feature+importances",
        "time": "2018-07-12T08:35:51.925Z",
        "products": [
            "Search"
        ],
        "locationInfos": [
            {
                "name": "At this general area",
                "url": "https://www.google.com/maps/@?api=1&map_action=map&center=40.183777,44.514705&zoom=11",
                "source": "Based on your past activity"
            }
        ]
    },
    {
        "header": "Search",
        "title": "Searched for irina ghaplanyan",
        "titleUrl": "https://www.google.com/search?q=irina+ghaplanyan",
        "time": "2018-07-11T15:55:26.490Z",
        "products": [
            "Search"
        ],
        "locationInfos": [
            {
                "name": "At this general area",
                "url": "https://www.google.com/maps/@?api=1&map_action=map&center=40.183777,44.514705&zoom=11",
                "source": "Based on your past activity"
            }
        ]
    },
    {
        "header": "Search",
        "title": "Searched for noodle",
        "titleUrl": "https://www.google.com/search?q=noodle",
        "time": "2018-07-11T15:20:14.677Z",
        "products": [
            "Search"
        ],
        "locationInfos": [
            {
                "name": "At this general area",
                "url": "https://www.google.com/maps/@?api=1&map_action=map&center=40.183777,44.514705&zoom=11",
                "source": "Based on your past activity"
            }
        ]
    },
    {
        "header": "Search",
        "title": "Searched for the words in magoosh gre app",
        "titleUrl": "https://www.google.com/search?q=the+words+in+magoosh+gre+app",
        "time": "2018-07-11T14:41:16.899Z",
        "products": [
            "Search"
        ],
        "locationInfos": [
            {
                "name": "At this general area",
                "url": "https://www.google.com/maps/@?api=1&map_action=map&center=40.183777,44.514705&zoom=11",
                "source": "Based on your past activity"
            }
        ]
    },
    {
        "header": "Search",
        "title": "Searched for the words in magoosh app",
        "titleUrl": "https://www.google.com/search?q=the+words+in+magoosh+app",
        "time": "2018-07-11T14:41:02.412Z",
        "products": [
            "Search"
        ],
        "locationInfos": [
            {
                "name": "At this general area",
                "url": "https://www.google.com/maps/@?api=1&map_action=map&center=40.183777,44.514705&zoom=11",
                "source": "Based on your past activity"
            }
        ]
    },
    {
        "header": "Search",
        "title": "Searched for export plotly as html file python",
        "titleUrl": "https://www.google.com/search?q=export+plotly+as+html+file+python",
        "time": "2018-07-11T11:56:28.716Z",
        "products": [
            "Search"
        ],
        "locationInfos": [
            {
                "name": "At this general area",
                "url": "https://www.google.com/maps/@?api=1&map_action=map&center=40.183777,44.514705&zoom=11",
                "source": "Based on your past activity"
            }
        ]
    },
    {
        "header": "Search",
        "title": "Searched for how to save plotly graph in python",
        "titleUrl": "https://www.google.com/search?q=how+to+save+plotly+graph+in+python",
        "time": "2018-07-11T11:51:26.146Z",
        "products": [
            "Search"
        ],
        "locationInfos": [
            {
                "name": "At this general area",
                "url": "https://www.google.com/maps/@?api=1&map_action=map&center=40.183777,44.514705&zoom=11",
                "source": "Based on your past activity"
            }
        ]
    },
    {
        "header": "Search",
        "title": "Searched for codeforces",
        "titleUrl": "https://www.google.com/search?q=codeforces",
        "time": "2018-07-11T11:43:53.937Z",
        "products": [
            "Search"
        ],
        "locationInfos": [
            {
                "name": "At this general area",
                "url": "https://www.google.com/maps/@?api=1&map_action=map&center=40.183777,44.514705&zoom=11",
                "source": "Based on your past activity"
            }
        ]
    },
    {
        "header": "Search",
        "title": "Searched for what is pinned repository in github",
        "titleUrl": "https://www.google.com/search?q=what+is+pinned+repository+in+github",
        "time": "2018-07-11T10:26:46.845Z",
        "products": [
            "Search"
        ],
        "locationInfos": [
            {
                "name": "At this general area",
                "url": "https://www.google.com/maps/@?api=1&map_action=map&center=40.183777,44.514705&zoom=11",
                "source": "Based on your past activity"
            }
        ]
    },
    {
        "header": "Search",
        "title": "Searched for how to improve loss and not accuracy keras",
        "titleUrl": "https://www.google.com/search?q=how+to+improve+loss+and+not+accuracy+keras",
        "time": "2018-07-11T10:13:51.605Z",
        "products": [
            "Search"
        ],
        "locationInfos": [
            {
                "name": "At this general area",
                "url": "https://www.google.com/maps/@?api=1&map_action=map&center=40.183777,44.514705&zoom=11",
                "source": "Based on your past activity"
            }
        ]
    },
    {
        "header": "Search",
        "title": "Searched for how to improve cross entropy loss keras",
        "titleUrl": "https://www.google.com/search?q=how+to+improve+cross+entropy+loss+keras",
        "time": "2018-07-11T10:11:48.660Z",
        "products": [
            "Search"
        ],
        "locationInfos": [
            {
                "name": "At this general area",
                "url": "https://www.google.com/maps/@?api=1&map_action=map&center=40.183777,44.514705&zoom=11",
                "source": "Based on your past activity"
            }
        ]
    },
    {
        "header": "Search",
        "title": "Searched for how to train model to have lower cross entropy loss",
        "titleUrl": "https://www.google.com/search?q=how+to+train+model+to+have+lower+cross+entropy+loss",
        "time": "2018-07-11T10:11:15.260Z",
        "products": [
            "Search"
        ],
        "locationInfos": [
            {
                "name": "At this general area",
                "url": "https://www.google.com/maps/@?api=1&map_action=map&center=40.183777,44.514705&zoom=11",
                "source": "Based on your past activity"
            }
        ]
    },
    {
        "header": "Search",
        "title": "Searched for cross entropy loss in keras",
        "titleUrl": "https://www.google.com/search?q=cross+entropy+loss+in+keras",
        "time": "2018-07-11T10:09:58.471Z",
        "products": [
            "Search"
        ],
        "locationInfos": [
            {
                "name": "At this general area",
                "url": "https://www.google.com/maps/@?api=1&map_action=map&center=40.183777,44.514705&zoom=11",
                "source": "Based on your past activity"
            }
        ]
    },
    {
        "header": "Search",
        "title": "Searched for keras",
        "titleUrl": "https://www.google.com/search?q=keras",
        "time": "2018-07-11T10:08:45.863Z",
        "products": [
            "Search"
        ],
        "locationInfos": [
            {
                "name": "At this general area",
                "url": "https://www.google.com/maps/@?api=1&map_action=map&center=40.183777,44.514705&zoom=11",
                "source": "Based on your past activity"
            }
        ]
    },
    {
        "header": "Search",
        "title": "Searched for validation accuracy increases but loss also increases",
        "titleUrl": "https://www.google.com/search?q=validation+accuracy+increases+but+loss+also+increases",
        "time": "2018-07-11T10:07:24.996Z",
        "products": [
            "Search"
        ],
        "locationInfos": [
            {
                "name": "At this general area",
                "url": "https://www.google.com/maps/@?api=1&map_action=map&center=40.183777,44.514705&zoom=11",
                "source": "Based on your past activity"
            }
        ]
    },
    {
        "header": "Search",
        "title": "Searched for regularizer keras",
        "titleUrl": "https://www.google.com/search?q=regularizer+keras",
        "time": "2018-07-11T09:52:31.440Z",
        "products": [
            "Search"
        ],
        "locationInfos": [
            {
                "name": "At this general area",
                "url": "https://www.google.com/maps/@?api=1&map_action=map&center=40.183777,44.514705&zoom=11",
                "source": "Based on your past activity"
            }
        ]
    },
    {
        "header": "Search",
        "title": "Searched for how to fight against overfitting keras",
        "titleUrl": "https://www.google.com/search?q=how+to+fight+against+overfitting+keras",
        "time": "2018-07-11T09:44:15.278Z",
        "products": [
            "Search"
        ],
        "locationInfos": [
            {
                "name": "At this general area",
                "url": "https://www.google.com/maps/@?api=1&map_action=map&center=40.183777,44.514705&zoom=11",
                "source": "Based on your past activity"
            }
        ]
    },
    {
        "header": "Search",
        "title": "Searched for magoosh",
        "titleUrl": "https://www.google.com/search?q=magoosh",
        "time": "2018-07-11T08:12:51.146Z",
        "products": [
            "Search"
        ],
        "locationInfos": [
            {
                "name": "At this general area",
                "url": "https://www.google.com/maps/@?api=1&map_action=map&center=40.183777,44.514705&zoom=11",
                "source": "Based on your past activity"
            }
        ]
    },
    {
        "header": "Search",
        "title": "Searched for what is qualify",
        "titleUrl": "https://www.google.com/search?q=what+is+qualify",
        "time": "2018-07-10T13:19:38.249Z",
        "products": [
            "Search"
        ],
        "locationInfos": [
            {
                "name": "At this general area",
                "url": "https://www.google.com/maps/@?api=1&map_action=map&center=40.183777,44.514705&zoom=11",
                "source": "Based on your past activity"
            }
        ]
    },
    {
        "header": "Search",
        "title": "Searched for meaning of cherished belief",
        "titleUrl": "https://www.google.com/search?q=meaning+of+cherished+belief",
        "time": "2018-07-10T12:36:59.892Z",
        "products": [
            "Search"
        ],
        "locationInfos": [
            {
                "name": "At this general area",
                "url": "https://www.google.com/maps/@?api=1&map_action=map&center=40.183777,44.514705&zoom=11",
                "source": "Based on your past activity"
            }
        ]
    },
    {
        "header": "Search",
        "title": "Searched for cherished meaning",
        "titleUrl": "https://www.google.com/search?q=cherished+meaning",
        "time": "2018-07-10T12:36:45.135Z",
        "products": [
            "Search"
        ],
        "locationInfos": [
            {
                "name": "At this general area",
                "url": "https://www.google.com/maps/@?api=1&map_action=map&center=40.183777,44.514705&zoom=11",
                "source": "Based on your past activity"
            }
        ]
    },
    {
        "header": "Search",
        "title": "Searched for lady gaga in \"meat dress\"",
        "titleUrl": "https://www.google.com/search?q=lady+gaga+in+%22meat+dress%22",
        "time": "2018-07-10T12:29:53.538Z",
        "products": [
            "Search"
        ],
        "locationInfos": [
            {
                "name": "At this general area",
                "url": "https://www.google.com/maps/@?api=1&map_action=map&center=40.183777,44.514705&zoom=11",
                "source": "Based on your past activity"
            }
        ]
    },
    {
        "header": "Search",
        "title": "Searched for lady gaga in \"mead dress\"",
        "titleUrl": "https://www.google.com/search?q=lady+gaga+in+%22mead+dress%22",
        "time": "2018-07-10T12:29:50.752Z",
        "products": [
            "Search"
        ],
        "locationInfos": [
            {
                "name": "At this general area",
                "url": "https://www.google.com/maps/@?api=1&map_action=map&center=40.183777,44.514705&zoom=11",
                "source": "Based on your past activity"
            }
        ]
    },
    {
        "header": "Search",
        "title": "Searched for cherish",
        "titleUrl": "https://www.google.com/search?q=cherish",
        "time": "2018-07-10T12:29:08.084Z",
        "products": [
            "Search"
        ],
        "locationInfos": [
            {
                "name": "At this general area",
                "url": "https://www.google.com/maps/@?api=1&map_action=map&center=40.183777,44.514705&zoom=11",
                "source": "Based on your past activity"
            }
        ]
    },
    {
        "header": "Search",
        "title": "Searched for cherisd",
        "titleUrl": "https://www.google.com/search?q=cherisd",
        "time": "2018-07-10T12:29:06.262Z",
        "products": [
            "Search"
        ],
        "locationInfos": [
            {
                "name": "At this general area",
                "url": "https://www.google.com/maps/@?api=1&map_action=map&center=40.183777,44.514705&zoom=11",
                "source": "Based on your past activity"
            }
        ]
    },
    {
        "header": "Search",
        "title": "Searched for whats is cherished belief",
        "titleUrl": "https://www.google.com/search?q=whats+is+cherished+belief",
        "time": "2018-07-10T12:27:22.106Z",
        "products": [
            "Search"
        ],
        "locationInfos": [
            {
                "name": "At this general area",
                "url": "https://www.google.com/maps/@?api=1&map_action=map&center=40.183777,44.514705&zoom=11",
                "source": "Based on your past activity"
            }
        ]
    },
    {
        "header": "Search",
        "title": "Searched for what is iconoclast",
        "titleUrl": "https://www.google.com/search?q=what+is+iconoclast",
        "time": "2018-07-10T12:27:13.333Z",
        "products": [
            "Search"
        ],
        "locationInfos": [
            {
                "name": "At this general area",
                "url": "https://www.google.com/maps/@?api=1&map_action=map&center=40.183777,44.514705&zoom=11",
                "source": "Based on your past activity"
            }
        ]
    },
    {
        "header": "Search",
        "title": "Searched for what is inconclast",
        "titleUrl": "https://www.google.com/search?q=what+is+inconclast",
        "time": "2018-07-10T12:13:57.993Z",
        "products": [
            "Search"
        ],
        "locationInfos": [
            {
                "name": "At this general area",
                "url": "https://www.google.com/maps/@?api=1&map_action=map&center=40.183777,44.514705&zoom=11",
                "source": "Based on your past activity"
            }
        ]
    },
    {
        "header": "Search",
        "title": "Searched for what is betray",
        "titleUrl": "https://www.google.com/search?q=what+is+betray",
        "time": "2018-07-10T11:45:52.081Z",
        "products": [
            "Search"
        ],
        "locationInfos": [
            {
                "name": "At this general area",
                "url": "https://www.google.com/maps/@?api=1&map_action=map&center=40.183777,44.514705&zoom=11",
                "source": "Based on your past activity"
            }
        ]
    },
    {
        "header": "Search",
        "title": "Searched for what is parochial",
        "titleUrl": "https://www.google.com/search?q=what+is+parochial",
        "time": "2018-07-10T11:40:17.461Z",
        "products": [
            "Search"
        ],
        "locationInfos": [
            {
                "name": "At this general area",
                "url": "https://www.google.com/maps/@?api=1&map_action=map&center=40.183777,44.514705&zoom=11",
                "source": "Based on your past activity"
            }
        ]
    },
    {
        "header": "Search",
        "title": "Searched for magoosh gre",
        "titleUrl": "https://www.google.com/search?q=magoosh+gre",
        "time": "2018-07-10T11:38:54.632Z",
        "products": [
            "Search"
        ],
        "locationInfos": [
            {
                "name": "At this general area",
                "url": "https://www.google.com/maps/@?api=1&map_action=map&center=40.183777,44.514705&zoom=11",
                "source": "Based on your past activity"
            }
        ]
    },
    {
        "header": "Search",
        "title": "Searched for magoosh",
        "titleUrl": "https://www.google.com/search?q=magoosh",
        "time": "2018-07-10T11:38:38.488Z",
        "products": [
            "Search"
        ],
        "locationInfos": [
            {
                "name": "At this general area",
                "url": "https://www.google.com/maps/@?api=1&map_action=map&center=40.183777,44.514705&zoom=11",
                "source": "Based on your past activity"
            }
        ]
    },
    {
        "header": "Search",
        "title": "Searched for what is restive",
        "titleUrl": "https://www.google.com/search?q=what+is+restive",
        "time": "2018-07-10T11:29:16.219Z",
        "products": [
            "Search"
        ],
        "locationInfos": [
            {
                "name": "At this general area",
                "url": "https://www.google.com/maps/@?api=1&map_action=map&center=40.183777,44.514705&zoom=11",
                "source": "Based on your past activity"
            }
        ]
    },
    {
        "header": "Search",
        "title": "Searched for magoosh gre",
        "titleUrl": "https://www.google.com/search?q=magoosh+gre",
        "time": "2018-07-10T11:04:09.566Z",
        "products": [
            "Search"
        ],
        "locationInfos": [
            {
                "name": "At this general area",
                "url": "https://www.google.com/maps/@?api=1&map_action=map&center=40.183777,44.514705&zoom=11",
                "source": "Based on your past activity"
            }
        ]
    },
    {
        "header": "Search",
        "title": "Searched for magoosh",
        "titleUrl": "https://www.google.com/search?q=magoosh",
        "time": "2018-07-10T11:04:06.352Z",
        "products": [
            "Search"
        ],
        "locationInfos": [
            {
                "name": "At this general area",
                "url": "https://www.google.com/maps/@?api=1&map_action=map&center=40.183777,44.514705&zoom=11",
                "source": "Based on your past activity"
            }
        ]
    },
    {
        "header": "Search",
        "title": "Searched for what is a one hot vector",
        "titleUrl": "https://www.google.com/search?q=what+is+a+one+hot+vector",
        "time": "2018-07-10T07:48:28.079Z",
        "products": [
            "Search"
        ],
        "locationInfos": [
            {
                "name": "At this general area",
                "url": "https://www.google.com/maps/@?api=1&map_action=map&center=40.183777,44.514705&zoom=11",
                "source": "Based on your past activity"
            }
        ]
    },
    {
        "header": "Search",
        "title": "Searched for nlp tasks",
        "titleUrl": "https://www.google.com/search?q=nlp+tasks",
        "time": "2018-07-10T07:42:54.612Z",
        "products": [
            "Search"
        ],
        "locationInfos": [
            {
                "name": "At this general area",
                "url": "https://www.google.com/maps/@?api=1&map_action=map&center=40.183777,44.514705&zoom=11",
                "source": "Based on your past activity"
            }
        ]
    },
    {
        "header": "Search",
        "title": "Searched for recurrent neural network",
        "titleUrl": "https://www.google.com/search?q=recurrent+neural+network",
        "time": "2018-07-10T07:41:37.960Z",
        "products": [
            "Search"
        ],
        "locationInfos": [
            {
                "name": "At this general area",
                "url": "https://www.google.com/maps/@?api=1&map_action=map&center=40.183777,44.514705&zoom=11",
                "source": "Based on your past activity"
            }
        ]
    },
    {
        "header": "Search",
        "title": "Searched for graphviz python value attribute not integer",
        "titleUrl": "https://www.google.com/search?q=graphviz+python+value+attribute+not+integer",
        "time": "2018-07-08T17:30:53.908Z",
        "products": [
            "Search"
        ],
        "locationInfos": [
            {
                "name": "At this general area",
                "url": "https://www.google.com/maps/@?api=1&map_action=map&center=40.183777,44.514705&zoom=12",
                "source": "Based on your past activity"
            }
        ]
    },
    {
        "header": "Search",
        "title": "Searched for graphviz value attribute not integer",
        "titleUrl": "https://www.google.com/search?q=graphviz+value+attribute+not+integer",
        "time": "2018-07-08T17:30:26.251Z",
        "products": [
            "Search"
        ],
        "locationInfos": [
            {
                "name": "At this general area",
                "url": "https://www.google.com/maps/@?api=1&map_action=map&center=40.183777,44.514705&zoom=12",
                "source": "Based on your past activity"
            }
        ]
    },
    {
        "header": "Search",
        "title": "Searched for graphviz does not show correct",
        "titleUrl": "https://www.google.com/search?q=graphviz+does+not+show+correct",
        "time": "2018-07-08T17:26:20.883Z",
        "products": [
            "Search"
        ],
        "locationInfos": [
            {
                "name": "At this general area",
                "url": "https://www.google.com/maps/@?api=1&map_action=map&center=40.183777,44.514705&zoom=12",
                "source": "Based on your past activity"
            }
        ]
    },
    {
        "header": "Search",
        "title": "Searched for why graphviz shows only part of samples",
        "titleUrl": "https://www.google.com/search?q=why+graphviz+shows+only+part+of+samples",
        "time": "2018-07-08T17:25:41.841Z",
        "products": [
            "Search"
        ],
        "locationInfos": [
            {
                "name": "At this general area",
                "url": "https://www.google.com/maps/@?api=1&map_action=map&center=40.183777,44.514705&zoom=12",
                "source": "Based on your past activity"
            }
        ]
    },
    {
        "header": "Search",
        "title": "Searched for anaconda forge install graphviz",
        "titleUrl": "https://www.google.com/search?q=anaconda+forge+install+graphviz",
        "time": "2018-07-08T17:21:39.566Z",
        "products": [
            "Search"
        ],
        "locationInfos": [
            {
                "name": "At this general area",
                "url": "https://www.google.com/maps/@?api=1&map_action=map&center=40.183777,44.514705&zoom=12",
                "source": "Based on your past activity"
            }
        ]
    },
    {
        "header": "Search",
        "title": "Searched for anaconda install graphviz",
        "titleUrl": "https://www.google.com/search?q=anaconda+install+graphviz",
        "time": "2018-07-08T17:21:26.963Z",
        "products": [
            "Search"
        ],
        "locationInfos": [
            {
                "name": "At this general area",
                "url": "https://www.google.com/maps/@?api=1&map_action=map&center=40.183777,44.514705&zoom=12",
                "source": "Based on your past activity"
            }
        ]
    },
    {
        "header": "Search",
        "title": "Searched for pydotplus anaconda",
        "titleUrl": "https://www.google.com/search?q=pydotplus+anaconda",
        "time": "2018-07-08T17:14:11.443Z",
        "products": [
            "Search"
        ],
        "locationInfos": [
            {
                "name": "At this general area",
                "url": "https://www.google.com/maps/@?api=1&map_action=map&center=40.183777,44.514705&zoom=12",
                "source": "Based on your past activity"
            }
        ]
    },
    {
        "header": "Search",
        "title": "Searched for how to visualize decision tree in python",
        "titleUrl": "https://www.google.com/search?q=how+to+visualize+decision+tree+in+python",
        "time": "2018-07-08T17:12:34.561Z",
        "products": [
            "Search"
        ],
        "locationInfos": [
            {
                "name": "At this general area",
                "url": "https://www.google.com/maps/@?api=1&map_action=map&center=40.183777,44.514705&zoom=12",
                "source": "Based on your past activity"
            }
        ]
    },
    {
        "header": "Search",
        "title": "Searched for gre test sample online",
        "titleUrl": "https://www.google.com/search?q=gre+test+sample+online",
        "time": "2018-07-08T15:58:06.598Z",
        "products": [
            "Search"
        ],
        "locationInfos": [
            {
                "name": "At this general area",
                "url": "https://www.google.com/maps/@?api=1&map_action=map&center=40.183777,44.514705&zoom=12",
                "source": "Based on your past activity"
            }
        ]
    },
    {
        "header": "Search",
        "title": "Searched for gre tests sample online",
        "titleUrl": "https://www.google.com/search?q=gre+tests+sample+online",
        "time": "2018-07-08T15:58:03.174Z",
        "products": [
            "Search"
        ],
        "locationInfos": [
            {
                "name": "At this general area",
                "url": "https://www.google.com/maps/@?api=1&map_action=map&center=40.183777,44.514705&zoom=12",
                "source": "Based on your past activity"
            }
        ]
    },
    {
        "header": "Search",
        "title": "Searched for gre tests online",
        "titleUrl": "https://www.google.com/search?q=gre+tests+online",
        "time": "2018-07-08T15:57:25.396Z",
        "products": [
            "Search"
        ],
        "locationInfos": [
            {
                "name": "At this general area",
                "url": "https://www.google.com/maps/@?api=1&map_action=map&center=40.183777,44.514705&zoom=12",
                "source": "Based on your past activity"
            }
        ]
    },
    {
        "header": "Search",
        "title": "Searched for world map",
        "titleUrl": "https://www.google.com/search?q=world+map",
        "time": "2018-07-03T15:29:31.873Z",
        "products": [
            "Search"
        ],
        "locationInfos": [
            {
                "name": "At this general area",
                "url": "https://www.google.com/maps/@?api=1&map_action=map&center=40.146879,44.498715&zoom=12",
                "source": "From your device"
            }
        ]
    }
]